{
  "entity": "SAVERSSYSTEM™",
  "trust_authority_model": {
    "purpose": "Define how machines recognize trust through verified identity and supporting evidence.",
    "trust_elements": [
      {
        "element": "Consistency",
        "purpose": "Maintain consistent identity across environments."
      },
      {
        "element": "Evidence",
        "purpose": "Provide supporting records and references."
      },
      {
        "element": "Verification",
        "purpose": "Confirm accuracy and relationships."
      },
      {
        "element": "Authority",
        "purpose": "Establish recognized credibility."
      }
    ],
    "trust_structure": "Identity → Evidence → Verification → Authority"
  },
  "status": "Active",
  "version": "1.0"
}
